LICENSE
MANIFEST.in
README.md
setup.py
django_support_form.egg-info/PKG-INFO
django_support_form.egg-info/SOURCES.txt
django_support_form.egg-info/dependency_links.txt
django_support_form.egg-info/requires.txt
django_support_form.egg-info/top_level.txt
supportform/__init__.py
supportform/forms.py
supportform/settings.py
supportform/urls.py
supportform/views.py
supportform/templates/supportform/email_body.txt
supportform/templates/supportform/form.html
supportform/templates/supportform/success.html