Metadata-Version: 1.0
Name: django-support-form
Version: 0.1.0
Summary: Simple support/contact form for your Django app
Home-page: https://github.com/cbmi/django-support-form/
Author: Byron Ruth
Author-email: b@devel.io
License: BSD
Keywords: support contact form
Platform: UNKNOWN
Classifier: Development Status :: 5 - Production/Stable
Classifier: License :: OSI Approved :: BSD License
Classifier: Programming Language :: Python :: 2.6
Classifier: Programming Language :: Python :: 2.7
Classifier: Framework :: Django
Classifier: Topic :: Internet :: WWW/HTTP
Classifier: Intended Audience :: Developers
